AUTHORS
ChangeLog
LICENSE
README.md
requirements.txt
setup.cfg
setup.py
test_requirements.txt
tox.ini
notabene/__init__.py
notabene/kombu_driver.py
notabene.egg-info/PKG-INFO
notabene.egg-info/SOURCES.txt
notabene.egg-info/dependency_links.txt
notabene.egg-info/not-zip-safe
notabene.egg-info/pbr.json
notabene.egg-info/requires.txt
notabene.egg-info/top_level.txt
tests/__init__.py
tests/test_kombu.py